ink/__init__.py
ink-0.0.1.dist-info/DESCRIPTION.rst
ink-0.0.1.dist-info/METADATA
ink-0.0.1.dist-info/RECORD
ink-0.0.1.dist-info/WHEEL
ink-0.0.1.dist-info/metadata.json
ink-0.0.1.dist-info/top_level.txt
tests/__init__.py
